{
	"info": {
		"_postman_id": "0e48f117-a4a8-49e7-889a-598117d1ef00",
		"name": "Notify",
		"schema": "https://schema.getpostman.com/json/collection/v2.1.0/collection.json"
	},
	"item": [
		{
			"name": "Get All Courses",
			"request": {
				"method": "GET",
				"header": [],
				"url": {
					"raw": "http://localhost:8083/api/courses",
					"protocol": "http",
					"host": [
						"localhost"
					],
					"port": "8083",
					"path": [
						"api",
						"courses"
					]
				}
			},
			"response": []
		},
		{
			"name": "Subscribe/Receive Pid for Course Details",
			"request": {
				"method": "GET",
				"header": [],
				"url": {
					"raw": "http://localhost:8083/api/subscribe",
					"protocol": "http",
					"host": [
						"localhost"
					],
					"port": "8083",
					"path": [
						"api",
						"subscribe"
					]
				}
			},
			"response": []
		},
		{
			"name": "Subscribe/Receive course name ",
			"request": {
				"method": "GET",
				"header": [],
				"url": {
					"raw": "http://localhost:8083/api/subscribe-course",
					"protocol": "http",
					"host": [
						"localhost"
					],
					"port": "8083",
					"path": [
						"api",
						"subscribe-course"
					]
				}
			},
			"response": []
		},
		{
			"name": "Subscribe/receive Username",
			"request": {
				"method": "GET",
				"header": [],
				"url": {
					"raw": "http://localhost:8083/api/notify",
					"protocol": "http",
					"host": [
						"localhost"
					],
					"port": "8083",
					"path": [
						"api",
						"notify"
					]
				}
			},
			"response": []
		}
	]
}